<?xml version="1.0" encoding="ISO-8859-1"?>
<Root_Element ID="DAOCUi">

<!-- @@ Edited with the DAoC User Interface Editor v1.80 -->
<!-- @@ Free download available at http://www.bradtownsend.com/daoced -->


    <WindowTemplate>
        <Name>custom0_window</Name>
        <WindowId>custom0_window</WindowId>
        <CloseButton>false</CloseButton>
        <MoveButton>false</MoveButton>
        <TopRightResizeButton>false</TopRightResizeButton>
        <BottomRightResizeButton>false</BottomRightResizeButton>
        <BottomLeftResizeButton>false</BottomLeftResizeButton>
        <ResizeButtonOffsetX>0</ResizeButtonOffsetX>
        <ResizeButtonOffsetY>0</ResizeButtonOffsetY>
        <TitleWidth>0</TitleWidth>
        <TitleHeight>0</TitleHeight>
        <Width>195</Width>
        <Height>180</Height>
        <ResizeableWidth>0</ResizeableWidth>
        <ResizeableHeight>0</ResizeableHeight>
        <ResizeableTwoWayWidth>0</ResizeableTwoWayWidth>
        <ResizeableTwoWayHeight>0</ResizeableTwoWayHeight>
        <MinWidth>0</MinWidth>
        <MinHeight>0</MinHeight>
        <ContextTemplateName></ContextTemplateName>


        <ImageAreaDef>
            <ControlId></ControlId>
            <Position>
                <X>0</X>
                <Y>0</Y>
            </Position>
            <Alignment>
                <TopLeft>true</TopLeft>
            </Alignment>
            <TemplateName>lym_menu_left</TemplateName>
        </ImageAreaDef>


        <StatusIconDef>
            <ControlId></ControlId>
            <Position>
                <X>0</X>
                <Y>0</Y>
            </Position>
            <Alignment>
                <TopLeft>true</TopLeft>
            </Alignment>
            <TemplateName>lym_attaque_menu_left</TemplateName>
            <AdapterName>combat_mode</AdapterName>
        </StatusIconDef>


        <ButtonDef>
            <ControlId></ControlId>
            <Position>
                <X>5</X>
                <Y>0</Y>
            </Position>
            <Alignment>
                <TopLeft>true</TopLeft>
            </Alignment>
            <TemplateName>lym_button1_left</TemplateName>
            <Label>Map</Label>
            <onClickEvent>ToggleMap</onClickEvent>
        </ButtonDef>


        <ButtonDef>
            <ControlId></ControlId>
            <Position>
                <X>99</X>
                <Y>33</Y>
            </Position>
            <Alignment>
                <TopLeft>true</TopLeft>
            </Alignment>
            <TemplateName>lym_button2_left</TemplateName>
            <Label>Journal</Label>
            <onClickEvent>ToggleJournal</onClickEvent>
        </ButtonDef>


        <ButtonDef>
            <ControlId></ControlId>
            <Position>
                <X>122</X>
                <Y>62</Y>
            </Position>
            <Alignment>
                <TopLeft>true</TopLeft>
            </Alignment>
            <TemplateName>lym_button3_left</TemplateName>
            <Label>MasterLevel</Label>
            <onClickEvent>ToggleMasterLevel</onClickEvent>
        </ButtonDef>


        <ButtonDef>
            <ControlId></ControlId>
            <Position>
                <X>136</X>
                <Y>91</Y>
            </Position>
            <Alignment>
                <TopLeft>true</TopLeft>
            </Alignment>
            <TemplateName>lym_button4_left</TemplateName>
            <Label>Invite</Label>
            <onClickEvent>GroupInvite</onClickEvent>
        </ButtonDef>


        <ButtonDef>
            <ControlId></ControlId>
            <Position>
                <X>145</X>
                <Y>120</Y>
            </Position>
            <Alignment>
                <TopLeft>true</TopLeft>
            </Alignment>
            <TemplateName>lym_button5_left</TemplateName>
            <Label>Disband</Label>
            <onClickEvent>GroupDisband</onClickEvent>
        </ButtonDef>


        <ButtonDef>
            <ControlId></ControlId>
            <Position>
                <X>149</X>
                <Y>149</Y>
            </Position>
            <Alignment>
                <TopLeft>true</TopLeft>
            </Alignment>
            <TemplateName>lym_button6_left</TemplateName>
            <Label>MiniGroup</Label>
            <onClickEvent>ToggleMiniGroup</onClickEvent>
        </ButtonDef>


        <ButtonDef>
            <ControlId></ControlId>
            <Position>
                <X>68</X>
                <Y>72</Y>
            </Position>
            <Alignment>
                <TopLeft>true</TopLeft>
            </Alignment>
            <TemplateName>lym_button0_small_blue</TemplateName>
            <Label>Bouton</Label>
            <onClickEvent>ToggleCustom7</onClickEvent>
        </ButtonDef>


        <ButtonDef>
            <ControlId></ControlId>
            <Position>
                <X>68</X>
                <Y>38</Y>
            </Position>
            <Alignment>
                <TopLeft>true</TopLeft>
            </Alignment>
            <TemplateName>lym_button0_small_green</TemplateName>
            <Label>Conc.</Label>
            <onClickEvent>ToggleConcentration</onClickEvent>
        </ButtonDef>


        <ButtonDef>
            <ControlId></ControlId>
            <Position>
                <X>68</X>
                <Y>55</Y>
            </Position>
            <Alignment>
                <TopLeft>true</TopLeft>
            </Alignment>
            <TemplateName>lym_button0_small_red</TemplateName>
            <Label>Résist</Label>
            <onClickEvent>ToggleCustom4</onClickEvent>
        </ButtonDef>


        <ButtonDef>
            <ControlId></ControlId>
            <Position>
                <X>5</X>
                <Y>55</Y>
            </Position>
            <Alignment>
                <TopLeft>true</TopLeft>
            </Alignment>
            <TemplateName>button_small</TemplateName>
            <Label>Bonus RvR</Label>
            <onClickEvent>WarmapUpdateBonuses</onClickEvent>
        </ButtonDef>


        <ButtonDef>
            <ControlId></ControlId>
            <Position>
                <X>5</X>
                <Y>38</Y>
            </Position>
            <Alignment>
                <TopLeft>true</TopLeft>
            </Alignment>
            <TemplateName>button_small</TemplateName>
            <Label>Options</Label>
            <onClickEvent>ToggleOptions</onClickEvent>
        </ButtonDef>


        <FullResizeImageDef>
            <ControlId></ControlId>
            <Position>
                <X>2</X>
                <Y>102</Y>
            </Position>
            <Alignment>
                <TopLeft>true</TopLeft>
            </Alignment>
            <TemplateName>selection_box_trans</TemplateName>
            <Width>130</Width>
            <Height>53</Height>
        </FullResizeImageDef>


        <LabelDef>
            <ControlId></ControlId>
            <Position>
                <X>4</X>
                <Y>154</Y>
            </Position>
            <Alignment>
                <TopLeft>true</TopLeft>
            </Alignment>
            <Color>
                <R>153</R>
                <G>153</G>
                <B>153</B>
                <A>255</A>
            </Color>
            <FontName>brit9</FontName>
            <Width>100</Width>
            <Height>25</Height>
            <ColorAdapter></ColorAdapter>
            <MaxCharacters>999</MaxCharacters>
            <Data>Heure irl :</Data>
            <EndAligned>false</EndAligned>
            <TextCentered>false</TextCentered>
            <Adapter></Adapter>
        </LabelDef>


        <LabelDef>
            <ControlId></ControlId>
            <Position>
                <X>4</X>
                <Y>164</Y>
            </Position>
            <Alignment>
                <TopLeft>true</TopLeft>
            </Alignment>
            <Color>
                <R>153</R>
                <G>153</G>
                <B>153</B>
                <A>255</A>
            </Color>
            <FontName>brit9</FontName>
            <Width>100</Width>
            <Height>25</Height>
            <ColorAdapter></ColorAdapter>
            <MaxCharacters>999</MaxCharacters>
            <Data>Heure DAoC :</Data>
            <EndAligned>false</EndAligned>
            <TextCentered>false</TextCentered>
            <Adapter></Adapter>
        </LabelDef>


        <LabelDef>
            <ControlId></ControlId>
            <Position>
                <X>60</X>
                <Y>154</Y>
            </Position>
            <Alignment>
                <TopLeft>true</TopLeft>
            </Alignment>
            <Color>
                <R>255</R>
                <G>255</G>
                <B>255</B>
                <A>255</A>
            </Color>
            <FontName>brit9</FontName>
            <Width>90</Width>
            <Height>25</Height>
            <ColorAdapter></ColorAdapter>
            <MaxCharacters>999</MaxCharacters>
            <Data></Data>
            <EndAligned>false</EndAligned>
            <TextCentered>false</TextCentered>
            <Adapter>time_of_day</Adapter>
        </LabelDef>


        <LabelDef>
            <ControlId></ControlId>
            <Position>
                <X>97</X>
                <Y>164</Y>
            </Position>
            <Alignment>
                <TopLeft>true</TopLeft>
            </Alignment>
            <Color>
                <R>255</R>
                <G>255</G>
                <B>255</B>
                <A>255</A>
            </Color>
            <FontName>brit9</FontName>
            <Width>40</Width>
            <Height>25</Height>
            <ColorAdapter></ColorAdapter>
            <MaxCharacters>999</MaxCharacters>
            <Data></Data>
            <EndAligned>false</EndAligned>
            <TextCentered>false</TextCentered>
            <Adapter>game_time</Adapter>
        </LabelDef>


        <ScalarLabelDef>
            <ControlId></ControlId>
            <Position>
                <X>5</X>
                <Y>103</Y>
            </Position>
            <Alignment>
                <TopLeft>true</TopLeft>
            </Alignment>
            <FontName>brit9</FontName>
            <Adapter>stats_strength</Adapter>
            <ColorAdapter>stats_strength_color</ColorAdapter>
            <Width>64</Width>
            <Height>16</Height>
            <MaxCharacters>128</MaxCharacters>
            <Color>
                <R>255</R>
                <G>255</G>
                <B>255</B>
                <A>255</A>
            </Color>
            <Data></Data>
            <EndAligned>false</EndAligned>
            <TextCentered>false</TextCentered>
            <DontDrawWhenZero>false</DontDrawWhenZero>
        </ScalarLabelDef>


        <LabelDef>
            <ControlId>1019</ControlId>
            <Position>
                <X>27</X>
                <Y>103</Y>
            </Position>
            <Alignment>
                <TopLeft>true</TopLeft>
            </Alignment>
            <ToolTipID>24</ToolTipID>
            <Color>
                <R>200</R>
                <G>200</G>
                <B>200</B>
                <A>200</A>
            </Color>
            <FontName>brit9</FontName>
            <Width>64</Width>
            <Height>18</Height>
            <ColorAdapter></ColorAdapter>
            <MaxCharacters>32</MaxCharacters>
            <Data>Force</Data>
            <EndAligned>false</EndAligned>
            <TextCentered>false</TextCentered>
            <Adapter></Adapter>
        </LabelDef>


        <ScalarLabelDef>
            <ControlId></ControlId>
            <Position>
                <X>5</X>
                <Y>115</Y>
            </Position>
            <Alignment>
                <TopLeft>true</TopLeft>
            </Alignment>
            <FontName>brit9</FontName>
            <Adapter>stats_constitution</Adapter>
            <ColorAdapter>stats_constitution_color</ColorAdapter>
            <Width>64</Width>
            <Height>16</Height>
            <MaxCharacters>128</MaxCharacters>
            <Color>
                <R>255</R>
                <G>255</G>
                <B>255</B>
                <A>255</A>
            </Color>
            <Data></Data>
            <EndAligned>false</EndAligned>
            <TextCentered>false</TextCentered>
            <DontDrawWhenZero>false</DontDrawWhenZero>
        </ScalarLabelDef>


        <LabelDef>
            <ControlId>1020</ControlId>
            <Position>
                <X>27</X>
                <Y>115</Y>
            </Position>
            <Alignment>
                <TopLeft>true</TopLeft>
            </Alignment>
            <ToolTipID>25</ToolTipID>
            <Color>
                <R>200</R>
                <G>200</G>
                <B>200</B>
                <A>200</A>
            </Color>
            <FontName>brit9</FontName>
            <Width>64</Width>
            <Height>18</Height>
            <ColorAdapter></ColorAdapter>
            <MaxCharacters>32</MaxCharacters>
            <Data>Constitution</Data>
            <EndAligned>false</EndAligned>
            <TextCentered>false</TextCentered>
            <Adapter></Adapter>
        </LabelDef>


        <ScalarLabelDef>
            <ControlId></ControlId>
            <Position>
                <X>5</X>
                <Y>127</Y>
            </Position>
            <Alignment>
                <TopLeft>true</TopLeft>
            </Alignment>
            <FontName>brit9</FontName>
            <Adapter>stats_dexterity</Adapter>
            <ColorAdapter>stats_dexterity_color</ColorAdapter>
            <Width>64</Width>
            <Height>16</Height>
            <MaxCharacters>128</MaxCharacters>
            <Color>
                <R>255</R>
                <G>255</G>
                <B>255</B>
                <A>255</A>
            </Color>
            <Data></Data>
            <EndAligned>false</EndAligned>
            <TextCentered>false</TextCentered>
            <DontDrawWhenZero>false</DontDrawWhenZero>
        </ScalarLabelDef>


        <LabelDef>
            <ControlId>1021</ControlId>
            <Position>
                <X>27</X>
                <Y>127</Y>
            </Position>
            <Alignment>
                <TopLeft>true</TopLeft>
            </Alignment>
            <ToolTipID>26</ToolTipID>
            <Color>
                <R>200</R>
                <G>200</G>
                <B>200</B>
                <A>200</A>
            </Color>
            <FontName>brit9</FontName>
            <Width>64</Width>
            <Height>18</Height>
            <ColorAdapter></ColorAdapter>
            <MaxCharacters>32</MaxCharacters>
            <Data>Dextérité</Data>
            <EndAligned>false</EndAligned>
            <TextCentered>false</TextCentered>
            <Adapter></Adapter>
        </LabelDef>


        <ScalarLabelDef>
            <ControlId></ControlId>
            <Position>
                <X>5</X>
                <Y>139</Y>
            </Position>
            <Alignment>
                <TopLeft>true</TopLeft>
            </Alignment>
            <FontName>brit9</FontName>
            <Adapter>stats_quickness</Adapter>
            <ColorAdapter>stats_quickness_color</ColorAdapter>
            <Width>64</Width>
            <Height>16</Height>
            <MaxCharacters>128</MaxCharacters>
            <Color>
                <R>255</R>
                <G>255</G>
                <B>255</B>
                <A>255</A>
            </Color>
            <Data></Data>
            <EndAligned>false</EndAligned>
            <TextCentered>false</TextCentered>
            <DontDrawWhenZero>false</DontDrawWhenZero>
        </ScalarLabelDef>


        <LabelDef>
            <ControlId>1022</ControlId>
            <Position>
                <X>27</X>
                <Y>139</Y>
            </Position>
            <Alignment>
                <TopLeft>true</TopLeft>
            </Alignment>
            <ToolTipID>27</ToolTipID>
            <Color>
                <R>200</R>
                <G>200</G>
                <B>200</B>
                <A>200</A>
            </Color>
            <FontName>brit9</FontName>
            <Width>64</Width>
            <Height>18</Height>
            <ColorAdapter></ColorAdapter>
            <MaxCharacters>32</MaxCharacters>
            <Data>Vivacité</Data>
            <EndAligned>false</EndAligned>
            <TextCentered>false</TextCentered>
            <Adapter></Adapter>
        </LabelDef>


        <ScalarLabelDef>
            <ControlId></ControlId>
            <Position>
                <X>85</X>
                <Y>103</Y>
            </Position>
            <Alignment>
                <TopLeft>true</TopLeft>
            </Alignment>
            <FontName>brit9</FontName>
            <Adapter>stats_intelligence</Adapter>
            <ColorAdapter>stats_intelligence_color</ColorAdapter>
            <Width>30</Width>
            <Height>16</Height>
            <MaxCharacters>128</MaxCharacters>
            <Color>
                <R>255</R>
                <G>255</G>
                <B>255</B>
                <A>255</A>
            </Color>
            <Data></Data>
            <EndAligned>false</EndAligned>
            <TextCentered>false</TextCentered>
            <DontDrawWhenZero>false</DontDrawWhenZero>
        </ScalarLabelDef>


        <LabelDef>
            <ControlId>1023</ControlId>
            <Position>
                <X>105</X>
                <Y>103</Y>
            </Position>
            <Alignment>
                <TopLeft>true</TopLeft>
            </Alignment>
            <ToolTipID>28</ToolTipID>
            <Color>
                <R>200</R>
                <G>200</G>
                <B>200</B>
                <A>200</A>
            </Color>
            <FontName>brit9</FontName>
            <Width>20</Width>
            <Height>18</Height>
            <ColorAdapter></ColorAdapter>
            <MaxCharacters>32</MaxCharacters>
            <Data>Intel.</Data>
            <EndAligned>false</EndAligned>
            <TextCentered>false</TextCentered>
            <Adapter></Adapter>
        </LabelDef>


        <ScalarLabelDef>
            <ControlId></ControlId>
            <Position>
                <X>85</X>
                <Y>115</Y>
            </Position>
            <Alignment>
                <TopLeft>true</TopLeft>
            </Alignment>
            <FontName>brit9</FontName>
            <Adapter>stats_empathy</Adapter>
            <ColorAdapter>stats_empathy_color</ColorAdapter>
            <Width>30</Width>
            <Height>16</Height>
            <MaxCharacters>128</MaxCharacters>
            <Color>
                <R>255</R>
                <G>255</G>
                <B>255</B>
                <A>255</A>
            </Color>
            <Data></Data>
            <EndAligned>false</EndAligned>
            <TextCentered>false</TextCentered>
            <DontDrawWhenZero>false</DontDrawWhenZero>
        </ScalarLabelDef>


        <LabelDef>
            <ControlId>1024</ControlId>
            <Position>
                <X>105</X>
                <Y>115</Y>
            </Position>
            <Alignment>
                <TopLeft>true</TopLeft>
            </Alignment>
            <ToolTipID>29</ToolTipID>
            <Color>
                <R>200</R>
                <G>200</G>
                <B>200</B>
                <A>200</A>
            </Color>
            <FontName>brit9</FontName>
            <Width>30</Width>
            <Height>18</Height>
            <ColorAdapter></ColorAdapter>
            <MaxCharacters>32</MaxCharacters>
            <Data>Empa.</Data>
            <EndAligned>false</EndAligned>
            <TextCentered>false</TextCentered>
            <Adapter></Adapter>
        </LabelDef>


        <ScalarLabelDef>
            <ControlId></ControlId>
            <Position>
                <X>85</X>
                <Y>127</Y>
            </Position>
            <Alignment>
                <TopLeft>true</TopLeft>
            </Alignment>
            <FontName>brit9</FontName>
            <Adapter>stats_piety</Adapter>
            <ColorAdapter>stats_piety_color</ColorAdapter>
            <Width>30</Width>
            <Height>16</Height>
            <MaxCharacters>128</MaxCharacters>
            <Color>
                <R>255</R>
                <G>255</G>
                <B>255</B>
                <A>255</A>
            </Color>
            <Data></Data>
            <EndAligned>false</EndAligned>
            <TextCentered>false</TextCentered>
            <DontDrawWhenZero>false</DontDrawWhenZero>
        </ScalarLabelDef>


        <LabelDef>
            <ControlId>1025</ControlId>
            <Position>
                <X>105</X>
                <Y>127</Y>
            </Position>
            <Alignment>
                <TopLeft>true</TopLeft>
            </Alignment>
            <ToolTipID>30</ToolTipID>
            <Color>
                <R>200</R>
                <G>200</G>
                <B>200</B>
                <A>200</A>
            </Color>
            <FontName>brit9</FontName>
            <Width>30</Width>
            <Height>18</Height>
            <ColorAdapter></ColorAdapter>
            <MaxCharacters>32</MaxCharacters>
            <Data>Piété</Data>
            <EndAligned>false</EndAligned>
            <TextCentered>false</TextCentered>
            <Adapter></Adapter>
        </LabelDef>


        <ScalarLabelDef>
            <ControlId></ControlId>
            <Position>
                <X>85</X>
                <Y>139</Y>
            </Position>
            <Alignment>
                <TopLeft>true</TopLeft>
            </Alignment>
            <FontName>brit9</FontName>
            <Adapter>stats_charisma</Adapter>
            <ColorAdapter>stats_charisma_color</ColorAdapter>
            <Width>30</Width>
            <Height>16</Height>
            <MaxCharacters>128</MaxCharacters>
            <Color>
                <R>255</R>
                <G>255</G>
                <B>255</B>
                <A>255</A>
            </Color>
            <Data></Data>
            <EndAligned>false</EndAligned>
            <TextCentered>false</TextCentered>
            <DontDrawWhenZero>false</DontDrawWhenZero>
        </ScalarLabelDef>


        <LabelDef>
            <ControlId>1026</ControlId>
            <Position>
                <X>105</X>
                <Y>139</Y>
            </Position>
            <Alignment>
                <TopLeft>true</TopLeft>
            </Alignment>
            <ToolTipID>31</ToolTipID>
            <Color>
                <R>200</R>
                <G>200</G>
                <B>200</B>
                <A>200</A>
            </Color>
            <FontName>brit9</FontName>
            <Width>30</Width>
            <Height>18</Height>
            <ColorAdapter></ColorAdapter>
            <MaxCharacters>32</MaxCharacters>
            <Data>Chari.</Data>
            <EndAligned>false</EndAligned>
            <TextCentered>false</TextCentered>
            <Adapter></Adapter>
        </LabelDef>


        <InvisibleButtonDef>
            <ControlId></ControlId>
            <Position>
                <X>3</X>
                <Y>104</Y>
            </Position>
            <Alignment>
                <TopLeft>true</TopLeft>
            </Alignment>
            <ToolTipID>1</ToolTipID>
            <Label></Label>
            <OnClickEvent></OnClickEvent>
            <Width>50</Width>
            <Height>13</Height>
        </InvisibleButtonDef>


        <InvisibleButtonDef>
            <ControlId></ControlId>
            <Position>
                <X>3</X>
                <Y>117</Y>
            </Position>
            <Alignment>
                <TopLeft>true</TopLeft>
            </Alignment>
            <ToolTipID>3</ToolTipID>
            <Label></Label>
            <OnClickEvent></OnClickEvent>
            <Width>74</Width>
            <Height>12</Height>
        </InvisibleButtonDef>


        <InvisibleButtonDef>
            <ControlId></ControlId>
            <Position>
                <X>4</X>
                <Y>129</Y>
            </Position>
            <Alignment>
                <TopLeft>true</TopLeft>
            </Alignment>
            <ToolTipID>2</ToolTipID>
            <Label></Label>
            <OnClickEvent></OnClickEvent>
            <Width>63</Width>
            <Height>12</Height>
        </InvisibleButtonDef>


        <InvisibleButtonDef>
            <ControlId></ControlId>
            <Position>
                <X>3</X>
                <Y>141</Y>
            </Position>
            <Alignment>
                <TopLeft>true</TopLeft>
            </Alignment>
            <ToolTipID>4</ToolTipID>
            <Label></Label>
            <OnClickEvent></OnClickEvent>
            <Width>63</Width>
            <Height>12</Height>
        </InvisibleButtonDef>


        <InvisibleButtonDef>
            <ControlId></ControlId>
            <Position>
                <X>83</X>
                <Y>103</Y>
            </Position>
            <Alignment>
                <TopLeft>true</TopLeft>
            </Alignment>
            <ToolTipID>5</ToolTipID>
            <Label></Label>
            <OnClickEvent></OnClickEvent>
            <Width>50</Width>
            <Height>12</Height>
        </InvisibleButtonDef>


        <InvisibleButtonDef>
            <ControlId></ControlId>
            <Position>
                <X>83</X>
                <Y>115</Y>
            </Position>
            <Alignment>
                <TopLeft>true</TopLeft>
            </Alignment>
            <ToolTipID>7</ToolTipID>
            <Label></Label>
            <OnClickEvent></OnClickEvent>
            <Width>50</Width>
            <Height>12</Height>
        </InvisibleButtonDef>


        <InvisibleButtonDef>
            <ControlId></ControlId>
            <Position>
                <X>83</X>
                <Y>128</Y>
            </Position>
            <Alignment>
                <TopLeft>true</TopLeft>
            </Alignment>
            <ToolTipID>6</ToolTipID>
            <Label></Label>
            <OnClickEvent></OnClickEvent>
            <Width>50</Width>
            <Height>12</Height>
        </InvisibleButtonDef>


        <InvisibleButtonDef>
            <ControlId></ControlId>
            <Position>
                <X>83</X>
                <Y>141</Y>
            </Position>
            <Alignment>
                <TopLeft>true</TopLeft>
            </Alignment>
            <ToolTipID>8</ToolTipID>
            <Label></Label>
            <OnClickEvent></OnClickEvent>
            <Width>50</Width>
            <Height>12</Height>
        </InvisibleButtonDef>


        <LabelDef>
            <ControlId></ControlId>
            <Position>
                <X>5</X>
                <Y>76</Y>
            </Position>
            <Alignment>
                <TopLeft>true</TopLeft>
            </Alignment>
            <Color>
                <R>200</R>
                <G>200</G>
                <B>200</B>
                <A>200</A>
            </Color>
            <FontName>brit9</FontName>
            <Width>64</Width>
            <Height>18</Height>
            <ColorAdapter></ColorAdapter>
            <MaxCharacters>32</MaxCharacters>
            <Data>Niveau:</Data>
            <EndAligned>false</EndAligned>
            <TextCentered>false</TextCentered>
            <Adapter></Adapter>
        </LabelDef>


        <LabelDef>
            <ControlId></ControlId>
            <Position>
                <X>5</X>
                <Y>89</Y>
            </Position>
            <Alignment>
                <TopLeft>true</TopLeft>
            </Alignment>
            <Color>
                <R>204</R>
                <G>204</G>
                <B>204</B>
                <A>200</A>
            </Color>
            <FontName>brit9</FontName>
            <Width>64</Width>
            <Height>18</Height>
            <ColorAdapter></ColorAdapter>
            <MaxCharacters>32</MaxCharacters>
            <Data>Attaque:</Data>
            <EndAligned>false</EndAligned>
            <TextCentered>false</TextCentered>
            <Adapter></Adapter>
        </LabelDef>


        <ScalarLabelDef>
            <ControlId></ControlId>
            <Position>
                <X>38</X>
                <Y>78</Y>
            </Position>
            <Alignment>
                <TopLeft>true</TopLeft>
            </Alignment>
            <FontName>arial9</FontName>
            <Adapter>stats_level</Adapter>
            <ColorAdapter></ColorAdapter>
            <Width>20</Width>
            <Height>18</Height>
            <MaxCharacters>32</MaxCharacters>
            <Color>
                <R>255</R>
                <G>255</G>
                <B>255</B>
                <A>255</A>
            </Color>
            <Data></Data>
            <EndAligned>false</EndAligned>
            <TextCentered>false</TextCentered>
            <DontDrawWhenZero>false</DontDrawWhenZero>
        </ScalarLabelDef>


        <ScalarLabelDef>
            <ControlId></ControlId>
            <Position>
                <X>42</X>
                <Y>89</Y>
            </Position>
            <Alignment>
                <TopLeft>true</TopLeft>
            </Alignment>
            <FontName>brit9</FontName>
            <Adapter>stats_weapon_skill</Adapter>
            <ColorAdapter></ColorAdapter>
            <Width>64</Width>
            <Height>16</Height>
            <MaxCharacters>128</MaxCharacters>
            <Color>
                <R>255</R>
                <G>255</G>
                <B>255</B>
                <A>255</A>
            </Color>
            <Data></Data>
            <EndAligned>false</EndAligned>
            <TextCentered>false</TextCentered>
            <DontDrawWhenZero>false</DontDrawWhenZero>
        </ScalarLabelDef>


        <LabelDef>
            <ControlId></ControlId>
            <Position>
                <X>67</X>
                <Y>89</Y>
            </Position>
            <Alignment>
                <TopLeft>true</TopLeft>
            </Alignment>
            <Color>
                <R>204</R>
                <G>204</G>
                <B>204</B>
                <A>200</A>
            </Color>
            <FontName>brit9</FontName>
            <Width>64</Width>
            <Height>18</Height>
            <ColorAdapter></ColorAdapter>
            <MaxCharacters>32</MaxCharacters>
            <Data>Pts de Vie:</Data>
            <EndAligned>false</EndAligned>
            <TextCentered>false</TextCentered>
            <Adapter></Adapter>
        </LabelDef>


        <ScalarLabelDef>
            <ControlId></ControlId>
            <Position>
                <X>112</X>
                <Y>91</Y>
            </Position>
            <Alignment>
                <TopLeft>true</TopLeft>
            </Alignment>
            <FontName>arial9</FontName>
            <Adapter>stats_hitpoints</Adapter>
            <ColorAdapter></ColorAdapter>
            <Width>25</Width>
            <Height>16</Height>
            <MaxCharacters>128</MaxCharacters>
            <Color>
                <R>255</R>
                <G>255</G>
                <B>255</B>
                <A>255</A>
            </Color>
            <Data></Data>
            <EndAligned>false</EndAligned>
            <TextCentered>false</TextCentered>
            <DontDrawWhenZero>false</DontDrawWhenZero>
        </ScalarLabelDef>


        <StatusIconDef>
            <ControlId>2000</ControlId>
            <Position>
                <X>6</X>
                <Y>21</Y>
            </Position>
            <Alignment>
                <TopLeft>true</TopLeft>
            </Alignment>
            <TemplateName>performance_icon_small</TemplateName>
            <AdapterName>performance_meter</AdapterName>
        </StatusIconDef>


        <StatusIconDef>
            <ControlId>2001</ControlId>
            <Position>
                <X>25</X>
                <Y>21</Y>
            </Position>
            <Alignment>
                <TopLeft>true</TopLeft>
            </Alignment>
            <TemplateName>performance_icon_small</TemplateName>
            <AdapterName>lag_meter</AdapterName>
        </StatusIconDef>


        <StatusIconDef>
            <ControlId>2002</ControlId>
            <Position>
                <X>44</X>
                <Y>21</Y>
            </Position>
            <Alignment>
                <TopLeft>true</TopLeft>
            </Alignment>
            <TemplateName>performance_icon_small</TemplateName>
            <AdapterName>framerate_meter</AdapterName>
        </StatusIconDef>


        <ButtonDef>
            <ControlId></ControlId>
            <Position>
                <X>2</X>
                <Y>2</Y>
            </Position>
            <Alignment>
                <TopLeft>true</TopLeft>
            </Alignment>
            <TemplateName>lym_close</TemplateName>
            <Label></Label>
            <onClickEvent>ToggleCustom0</onClickEvent>
        </ButtonDef>


        <ScalarLabelDef>
            <ControlId></ControlId>
            <Position>
                <X>6</X>
                <Y>9</Y>
            </Position>
            <Alignment>
                <TopLeft>true</TopLeft>
            </Alignment>
            <FontName>brit9</FontName>
            <Adapter></Adapter>
            <ColorAdapter></ColorAdapter>
            <Width>17</Width>
            <Height>15</Height>
            <MaxCharacters>999</MaxCharacters>
            <Color>
                <R>204</R>
                <G>204</G>
                <B>204</B>
                <A>255</A>
            </Color>
            <Data>ram</Data>
            <EndAligned>false</EndAligned>
            <TextCentered>false</TextCentered>
            <DontDrawWhenZero>false</DontDrawWhenZero>
        </ScalarLabelDef>


        <ScalarLabelDef>
            <ControlId></ControlId>
            <Position>
                <X>27</X>
                <Y>9</Y>
            </Position>
            <Alignment>
                <TopLeft>true</TopLeft>
            </Alignment>
            <FontName>brit9</FontName>
            <Adapter></Adapter>
            <ColorAdapter></ColorAdapter>
            <Width>15</Width>
            <Height>15</Height>
            <MaxCharacters>999</MaxCharacters>
            <Color>
                <R>204</R>
                <G>204</G>
                <B>204</B>
                <A>255</A>
            </Color>
            <Data>lag</Data>
            <EndAligned>false</EndAligned>
            <TextCentered>false</TextCentered>
            <DontDrawWhenZero>false</DontDrawWhenZero>
        </ScalarLabelDef>


        <ScalarLabelDef>
            <ControlId></ControlId>
            <Position>
                <X>44</X>
                <Y>9</Y>
            </Position>
            <Alignment>
                <TopLeft>true</TopLeft>
            </Alignment>
            <FontName>brit9</FontName>
            <Adapter></Adapter>
            <ColorAdapter></ColorAdapter>
            <Width>15</Width>
            <Height>15</Height>
            <MaxCharacters>999</MaxCharacters>
            <Color>
                <R>204</R>
                <G>204</G>
                <B>204</B>
                <A>255</A>
            </Color>
            <Data>fps</Data>
            <EndAligned>false</EndAligned>
            <TextCentered>false</TextCentered>
            <DontDrawWhenZero>false</DontDrawWhenZero>
        </ScalarLabelDef>


        <ImageAreaDef>
            <ControlId></ControlId>
            <Position>
                <X>94</X>
                <Y>17</Y>
            </Position>
            <Alignment>
                <TopLeft>true</TopLeft>
            </Alignment>
            <TemplateName>lym_map_small</TemplateName>
        </ImageAreaDef>


        <ImageAreaDef>
            <ControlId></ControlId>
            <Position>
                <X>125</X>
                <Y>40</Y>
            </Position>
            <Alignment>
                <TopLeft>true</TopLeft>
            </Alignment>
            <TemplateName>lym_journal_small</TemplateName>
        </ImageAreaDef>


        <ImageAreaDef>
            <ControlId></ControlId>
            <Position>
                <X>140</X>
                <Y>68</Y>
            </Position>
            <Alignment>
                <TopLeft>true</TopLeft>
            </Alignment>
            <TemplateName>lym_ml_small</TemplateName>
        </ImageAreaDef>


        <ImageAreaDef>
            <ControlId></ControlId>
            <Position>
                <X>154</X>
                <Y>99</Y>
            </Position>
            <Alignment>
                <TopLeft>true</TopLeft>
            </Alignment>
            <TemplateName>lym_invite</TemplateName>
        </ImageAreaDef>


        <ImageAreaDef>
            <ControlId></ControlId>
            <Position>
                <X>160</X>
                <Y>128</Y>
            </Position>
            <Alignment>
                <TopLeft>true</TopLeft>
            </Alignment>
            <TemplateName>lym_disband</TemplateName>
        </ImageAreaDef>


        <ImageAreaDef>
            <ControlId></ControlId>
            <Position>
                <X>163</X>
                <Y>156</Y>
            </Position>
            <Alignment>
                <TopLeft>true</TopLeft>
            </Alignment>
            <TemplateName>lym_groupe_small</TemplateName>
        </ImageAreaDef>


    </WindowTemplate>


</Root_Element>
