<?xml version="1.0" encoding="ISO-8859-1"?>
<Root_Element ID="DAOCUi">
	<MenuTemplate>
		<Name>menu_thin</Name>
		<Width>120</Width>
		<Height>16</Height>
		<LabelLength>128</LabelLength>
		<Font>
			<Name>arial11</Name>
			<ColorNormal>
				<R>192</R>
				<G>192</G>
				<B>192</B>
				<A>255</A>
			</ColorNormal>
			<ColorHighlit>
				<R>255</R>
				<G>192</G>
				<B>0</B>
				<A>255</A>
			</ColorHighlit>
		</Font>
		<Texture>
			<TextureName>page3</TextureName>
			<Normal>
				<X>39</X>
				<Y>108</Y>
			</Normal>
			<Highlit>
				<X>39</X>
				<Y>87</Y>
			</Highlit>
		</Texture>
	</MenuTemplate>
	<ComboBoxTemplate>
		<Name>combobox_thin</Name>
		<DownButtonTemplate>button_down</DownButtonTemplate>
		<LabelButtonTemplate>combo_label</LabelButtonTemplate>
		<MenuTemplate>menu_thin</MenuTemplate>
		<MenuOffset>
			<X>5</X>
			<Y>0</Y>
		</MenuOffset>
	</ComboBoxTemplate>
	<WindowTemplate>
		<Name>looking_for_group</Name>
		<CloseButton>true</CloseButton>
		<MoveButton>true</MoveButton>
		<Width>440</Width>
		<Height>330</Height>
		<TitleWidth>416</TitleWidth>
		<TitleHeight>18</TitleHeight>
		<ResizeableWidth>0</ResizeableWidth>
		<ResizeableHeight>0</ResizeableHeight>
		<ResizeableTwoWayWidth>0</ResizeableTwoWayWidth>
		<ResizeableTwoWayHeight>0</ResizeableTwoWayHeight>
		<WindowId>c_windowInvalid</WindowId>
		<MinWidth>0</MinWidth>
		<MinHeight>0</MinHeight>
		<FullResizeImageDef>
			<ControlId>BackgroundImage</ControlId>
			<Width>440</Width>
			<Height>330</Height>
			<Position>
				<X>0</X>
				<Y>0</Y>
			</Position>
			<TemplateName>dlg_lg_title_noresize</TemplateName>
			<LabelDef>
				<Color>
					<R>255</R>
					<G>255</G>
					<B>255</B>
					<A>255</A>
				</Color>
				<FontName>arial11</FontName>
				<Width>75</Width>
				<Height>16</Height>
				<MaxCharacters>64</MaxCharacters>
				<Data>Looking For Group</Data>
				<Position>
					<X>0</X>
					<Y>4</Y>
				</Position>
				<Alignment>
					<CenterHorizontally>true</CenterHorizontally>
				</Alignment>
				<Adapter>lfg_title</Adapter>
			</LabelDef>
		</FullResizeImageDef>
		<LabelDef>
			<Color>
				<R>255</R>
				<G>255</G>
				<B>255</B>
				<A>255</A>
			</Color>
			<FontName>arial11</FontName>
			<Width>150</Width>
			<Height>16</Height>
			<MaxCharacters>128</MaxCharacters>
			<Position>
				<X>0</X>
				<Y>4</Y>
			</Position>
			<Alignment>
				<CenterHorizontally>true</CenterHorizontally>
			</Alignment>
			<Adapter>lfg_title</Adapter>
		</LabelDef>
		<CheckBoxDef>
			<Position>
				<X>216</X>
				<Y>47</Y>
			</Position>
			<ControlId>1100</ControlId>
			<TemplateName>narrow_font_check</TemplateName>
			<Data>ML0.1</Data>
			<LabelWidth>55</LabelWidth>
		</CheckBoxDef>
		<CheckBoxDef>
			<Position>
				<X>286</X>
				<Y>47</Y>
			</Position>
			<ControlId>1101</ControlId>
			<TemplateName>narrow_font_check</TemplateName>
			<Data>ML0.2</Data>
			<LabelWidth>55</LabelWidth>
		</CheckBoxDef>
		<CheckBoxDef>
			<Position>
				<X>356</X>
				<Y>47</Y>
			</Position>
			<ControlId>1102</ControlId>
			<TemplateName>narrow_font_check</TemplateName>
			<Data>ML0.3</Data>
			<LabelWidth>55</LabelWidth>
		</CheckBoxDef>
		<CheckBoxDef>
			<Position>
				<X>216</X>
				<Y>65</Y>
			</Position>
			<ControlId>1103</ControlId>
			<TemplateName>narrow_font_check</TemplateName>
			<Data>ML0.4</Data>
			<LabelWidth>55</LabelWidth>
		</CheckBoxDef>
		<CheckBoxDef>
			<Position>
				<X>286</X>
				<Y>65</Y>
			</Position>
			<ControlId>1104</ControlId>
			<TemplateName>narrow_font_check</TemplateName>
			<Data>ML0.5</Data>
			<LabelWidth>55</LabelWidth>
		</CheckBoxDef>
		<CheckBoxDef>
			<Position>
				<X>356</X>
				<Y>65</Y>
			</Position>
			<ControlId>1105</ControlId>
			<TemplateName>narrow_font_check</TemplateName>
			<Data>ML0.6</Data>
			<LabelWidth>55</LabelWidth>
		</CheckBoxDef>
		<CheckBoxDef>
			<Position>
				<X>216</X>
				<Y>83</Y>
			</Position>
			<ControlId>1106</ControlId>
			<TemplateName>narrow_font_check</TemplateName>
			<Data>ML0.7</Data>
			<LabelWidth>55</LabelWidth>
		</CheckBoxDef>
		<CheckBoxDef>
			<Position>
				<X>286</X>
				<Y>83</Y>
			</Position>
			<ControlId>1107</ControlId>
			<TemplateName>narrow_font_check</TemplateName>
			<Data>ML0.8</Data>
			<LabelWidth>55</LabelWidth>
		</CheckBoxDef>
		<CheckBoxDef>
			<Position>
				<X>356</X>
				<Y>83</Y>
			</Position>
			<ControlId>1108</ControlId>
			<TemplateName>narrow_font_check</TemplateName>
			<Data>ML0.9</Data>
			<LabelWidth>55</LabelWidth>
		</CheckBoxDef>
		<CheckBoxDef>
			<Position>
				<X>216</X>
				<Y>101</Y>
			</Position>
			<ControlId>1109</ControlId>
			<TemplateName>narrow_font_check</TemplateName>
			<Data>ML0.10</Data>
			<LabelWidth>55</LabelWidth>
		</CheckBoxDef>
		<CheckBoxDef>
			<Position>
				<X>286</X>
				<Y>101</Y>
			</Position>
			<ControlId>1110</ControlId>
			<TemplateName>narrow_font_check</TemplateName>
			<Data>ML EXP</Data>
			<LabelWidth>55</LabelWidth>
		</CheckBoxDef>
		<LabelDef>
			<Color>
				<R>192</R>
				<G>192</G>
				<B>192</B>
				<A>255</A>
			</Color>
			<FontName>arial11</FontName>
			<Width>150</Width>
			<Height>16</Height>
			<MaxCharacters>64</MaxCharacters>
			<Data>Class Selection</Data>
			<Position>
				<X>13</X>
				<Y>140</Y>
			</Position>
		</LabelDef>
		<ButtonDef>
			<TemplateName>button_large</TemplateName>
			<ControlId>1011</ControlId>
			<Position>
				<X>13</X>
				<Y>156</Y>
			</Position>
			<Label>ALL</Label>
		</ButtonDef>
		<ButtonDef>
			<TemplateName>button_large</TemplateName>
			<ControlId>1012</ControlId>
			<Position>
				<X>13</X>
				<Y>176</Y>
			</Position>
			<Label>FIGHTER</Label>
		</ButtonDef>
		<ButtonDef>
			<TemplateName>button_large</TemplateName>
			<ControlId>1013</ControlId>
			<Position>
				<X>13</X>
				<Y>196</Y>
			</Position>
			<Label>MAGE</Label>
		</ButtonDef>
		<ButtonDef>
			<TemplateName>button_large</TemplateName>
			<Position>
				<X>13</X>
				<Y>216</Y>
			</Position>
			<ControlId>1014</ControlId>
			<Label>ROGUE</Label>
		</ButtonDef>
		<ButtonDef>
			<TemplateName>button_large</TemplateName>
			<ControlId>1015</ControlId>
			<Position>
				<X>13</X>
				<Y>236</Y>
			</Position>
			<Label>HEALER</Label>
		</ButtonDef>
		<ButtonDef>
			<TemplateName>button_large</TemplateName>
			<ControlId>1016</ControlId>
			<Position>
				<X>13</X>
				<Y>256</Y>
			</Position>
			<Label>NONE</Label>
		</ButtonDef>
		<CheckBoxDef>
			<Position>
				<X>76</X>
				<Y>156</Y>
			</Position>
			<ControlId>1200</ControlId>
			<TemplateName>narrow_font_check</TemplateName>
			<Data>class0</Data>
			<LabelWidth>55</LabelWidth>
		</CheckBoxDef>
		<CheckBoxDef>
			<Position>
				<X>76</X>
				<Y>170</Y>
			</Position>
			<ControlId>1201</ControlId>
			<TemplateName>narrow_font_check</TemplateName>
			<Data>class1</Data>
			<LabelWidth>55</LabelWidth>
		</CheckBoxDef>
		<CheckBoxDef>
			<Position>
				<X>76</X>
				<Y>184</Y>
			</Position>
			<ControlId>1202</ControlId>
			<TemplateName>narrow_font_check</TemplateName>
			<Data>class2</Data>
			<LabelWidth>55</LabelWidth>
		</CheckBoxDef>
		<CheckBoxDef>
			<Position>
				<X>76</X>
				<Y>198</Y>
			</Position>
			<ControlId>1203</ControlId>
			<TemplateName>narrow_font_check</TemplateName>
			<Data>class3</Data>
			<LabelWidth>55</LabelWidth>
		</CheckBoxDef>
		<CheckBoxDef>
			<Position>
				<X>76</X>
				<Y>212</Y>
			</Position>
			<ControlId>1204</ControlId>
			<TemplateName>narrow_font_check</TemplateName>
			<Data>class4</Data>
			<LabelWidth>55</LabelWidth>
		</CheckBoxDef>
		<CheckBoxDef>
			<Position>
				<X>76</X>
				<Y>226</Y>
			</Position>
			<ControlId>1205</ControlId>
			<TemplateName>narrow_font_check</TemplateName>
			<Data>class5</Data>
			<LabelWidth>55</LabelWidth>
		</CheckBoxDef>
		<CheckBoxDef>
			<Position>
				<X>76</X>
				<Y>240</Y>
			</Position>
			<ControlId>1206</ControlId>
			<TemplateName>narrow_font_check</TemplateName>
			<Data>class6</Data>
			<LabelWidth>55</LabelWidth>
		</CheckBoxDef>
		<CheckBoxDef>
			<Position>
				<X>76</X>
				<Y>254</Y>
			</Position>
			<ControlId>1207</ControlId>
			<TemplateName>narrow_font_check</TemplateName>
			<Data>class7</Data>
			<LabelWidth>55</LabelWidth>
		</CheckBoxDef>
		<CheckBoxDef>
			<Position>
				<X>76</X>
				<Y>268</Y>
			</Position>
			<ControlId>1208</ControlId>
			<TemplateName>narrow_font_check</TemplateName>
			<Data>class8</Data>
			<LabelWidth>55</LabelWidth>
		</CheckBoxDef>
		<CheckBoxDef>
			<Position>
				<X>76</X>
				<Y>282</Y>
			</Position>
			<ControlId>1209</ControlId>
			<TemplateName>narrow_font_check</TemplateName>
			<Data>class9</Data>
			<LabelWidth>55</LabelWidth>
		</CheckBoxDef>
		<CheckBoxDef>
			<Position>
				<X>146</X>
				<Y>156</Y>
			</Position>
			<ControlId>1210</ControlId>
			<TemplateName>narrow_font_check</TemplateName>
			<Data>class10</Data>
			<LabelWidth>55</LabelWidth>
		</CheckBoxDef>
		<CheckBoxDef>
			<Position>
				<X>146</X>
				<Y>170</Y>
			</Position>
			<ControlId>1211</ControlId>
			<TemplateName>narrow_font_check</TemplateName>
			<Data>class11</Data>
			<LabelWidth>55</LabelWidth>
		</CheckBoxDef>
		<CheckBoxDef>
			<Position>
				<X>146</X>
				<Y>184</Y>
			</Position>
			<ControlId>1212</ControlId>
			<TemplateName>narrow_font_check</TemplateName>
			<Data>class12</Data>
			<LabelWidth>55</LabelWidth>
		</CheckBoxDef>
		<CheckBoxDef>
			<Position>
				<X>146</X>
				<Y>198</Y>
			</Position>
			<ControlId>1213</ControlId>
			<TemplateName>narrow_font_check</TemplateName>
			<Data>class13</Data>
			<LabelWidth>55</LabelWidth>
		</CheckBoxDef>
		<CheckBoxDef>
			<Position>
				<X>146</X>
				<Y>212</Y>
			</Position>
			<ControlId>1214</ControlId>
			<TemplateName>narrow_font_check</TemplateName>
			<Data>class14</Data>
			<LabelWidth>55</LabelWidth>
		</CheckBoxDef>
		<CheckBoxDef>
			<Position>
				<X>146</X>
				<Y>226</Y>
			</Position>
			<ControlId>1215</ControlId>
			<TemplateName>narrow_font_check</TemplateName>
			<Data>class15</Data>
			<LabelWidth>55</LabelWidth>
		</CheckBoxDef>
		<CheckBoxDef>
			<Position>
				<X>146</X>
				<Y>240</Y>
			</Position>
			<ControlId>1216</ControlId>
			<TemplateName>narrow_font_check</TemplateName>
			<Data>class16</Data>
			<LabelWidth>55</LabelWidth>
		</CheckBoxDef>
		<CheckBoxDef>
			<Position>
				<X>146</X>
				<Y>254</Y>
			</Position>
			<ControlId>1217</ControlId>
			<TemplateName>narrow_font_check</TemplateName>
			<Data>class17</Data>
			<LabelWidth>55</LabelWidth>
		</CheckBoxDef>
		<CheckBoxDef>
			<Position>
				<X>146</X>
				<Y>268</Y>
			</Position>
			<ControlId>1218</ControlId>
			<TemplateName>narrow_font_check</TemplateName>
			<Data>class18</Data>
			<LabelWidth>55</LabelWidth>
		</CheckBoxDef>
		<CheckBoxDef>
			<Position>
				<X>146</X>
				<Y>282</Y>
			</Position>
			<ControlId>1219</ControlId>
			<TemplateName>narrow_font_check</TemplateName>
			<Data>class19</Data>
			<LabelWidth>55</LabelWidth>
		</CheckBoxDef>
		<CheckBoxDef>
			<Position>
				<X>216</X>
				<Y>156</Y>
			</Position>
			<ControlId>1220</ControlId>
			<TemplateName>narrow_font_check</TemplateName>
			<Data>class20</Data>
			<LabelWidth>55</LabelWidth>
		</CheckBoxDef>
		<CheckBoxDef>
			<Position>
				<X>216</X>
				<Y>170</Y>
			</Position>
			<ControlId>1221</ControlId>
			<TemplateName>narrow_font_check</TemplateName>
			<Data>class21</Data>
			<LabelWidth>55</LabelWidth>
		</CheckBoxDef>
		<CheckBoxDef>
			<Position>
				<X>216</X>
				<Y>184</Y>
			</Position>
			<ControlId>1222</ControlId>
			<TemplateName>narrow_font_check</TemplateName>
			<Data>class22</Data>
			<LabelWidth>55</LabelWidth>
		</CheckBoxDef>
		<CheckBoxDef>
			<Position>
				<X>216</X>
				<Y>198</Y>
			</Position>
			<ControlId>1223</ControlId>
			<TemplateName>narrow_font_check</TemplateName>
			<Data>class23</Data>
			<LabelWidth>55</LabelWidth>
		</CheckBoxDef>
		<CheckBoxDef>
			<Position>
				<X>216</X>
				<Y>212</Y>
			</Position>
			<ControlId>1224</ControlId>
			<TemplateName>narrow_font_check</TemplateName>
			<Data>class24</Data>
			<LabelWidth>55</LabelWidth>
		</CheckBoxDef>
		<CheckBoxDef>
			<Position>
				<X>216</X>
				<Y>226</Y>
			</Position>
			<ControlId>1225</ControlId>
			<TemplateName>narrow_font_check</TemplateName>
			<Data>class25</Data>
			<LabelWidth>55</LabelWidth>
		</CheckBoxDef>
		<CheckBoxDef>
			<Position>
				<X>216</X>
				<Y>240</Y>
			</Position>
			<ControlId>1226</ControlId>
			<TemplateName>narrow_font_check</TemplateName>
			<Data>class26</Data>
			<LabelWidth>55</LabelWidth>
		</CheckBoxDef>
		<CheckBoxDef>
			<Position>
				<X>216</X>
				<Y>254</Y>
			</Position>
			<ControlId>1227</ControlId>
			<TemplateName>narrow_font_check</TemplateName>
			<Data>class27</Data>
			<LabelWidth>55</LabelWidth>
		</CheckBoxDef>
		<CheckBoxDef>
			<Position>
				<X>216</X>
				<Y>268</Y>
			</Position>
			<ControlId>1228</ControlId>
			<TemplateName>narrow_font_check</TemplateName>
			<Data>class28</Data>
			<LabelWidth>55</LabelWidth>
		</CheckBoxDef>
		<CheckBoxDef>
			<Position>
				<X>216</X>
				<Y>282</Y>
			</Position>
			<ControlId>1229</ControlId>
			<TemplateName>narrow_font_check</TemplateName>
			<Data>class29</Data>
			<LabelWidth>55</LabelWidth>
		</CheckBoxDef>
		<CheckBoxDef>
			<Position>
				<X>286</X>
				<Y>156</Y>
			</Position>
			<ControlId>1230</ControlId>
			<TemplateName>narrow_font_check</TemplateName>
			<Data>class30</Data>
			<LabelWidth>55</LabelWidth>
		</CheckBoxDef>
		<CheckBoxDef>
			<Position>
				<X>286</X>
				<Y>170</Y>
			</Position>
			<ControlId>1231</ControlId>
			<TemplateName>narrow_font_check</TemplateName>
			<Data>class31</Data>
			<LabelWidth>55</LabelWidth>
		</CheckBoxDef>
		<CheckBoxDef>
			<Position>
				<X>286</X>
				<Y>184</Y>
			</Position>
			<ControlId>1232</ControlId>
			<TemplateName>narrow_font_check</TemplateName>
			<Data>class32</Data>
			<LabelWidth>55</LabelWidth>
		</CheckBoxDef>
		<CheckBoxDef>
			<Position>
				<X>286</X>
				<Y>198</Y>
			</Position>
			<ControlId>1233</ControlId>
			<TemplateName>narrow_font_check</TemplateName>
			<Data>class33</Data>
			<LabelWidth>55</LabelWidth>
		</CheckBoxDef>
		<CheckBoxDef>
			<Position>
				<X>286</X>
				<Y>212</Y>
			</Position>
			<ControlId>1234</ControlId>
			<TemplateName>narrow_font_check</TemplateName>
			<Data>class34</Data>
			<LabelWidth>55</LabelWidth>
		</CheckBoxDef>
		<CheckBoxDef>
			<Position>
				<X>286</X>
				<Y>226</Y>
			</Position>
			<ControlId>1235</ControlId>
			<TemplateName>narrow_font_check</TemplateName>
			<Data>class35</Data>
			<LabelWidth>55</LabelWidth>
		</CheckBoxDef>
		<CheckBoxDef>
			<Position>
				<X>286</X>
				<Y>240</Y>
			</Position>
			<ControlId>1236</ControlId>
			<TemplateName>narrow_font_check</TemplateName>
			<Data>class36</Data>
			<LabelWidth>55</LabelWidth>
		</CheckBoxDef>
		<CheckBoxDef>
			<Position>
				<X>286</X>
				<Y>254</Y>
			</Position>
			<ControlId>1237</ControlId>
			<TemplateName>narrow_font_check</TemplateName>
			<Data>class37</Data>
			<LabelWidth>55</LabelWidth>
		</CheckBoxDef>
		<CheckBoxDef>
			<Position>
				<X>286</X>
				<Y>268</Y>
			</Position>
			<ControlId>1238</ControlId>
			<TemplateName>narrow_font_check</TemplateName>
			<Data>class38</Data>
			<LabelWidth>55</LabelWidth>
		</CheckBoxDef>
		<CheckBoxDef>
			<Position>
				<X>286</X>
				<Y>282</Y>
			</Position>
			<ControlId>1239</ControlId>
			<TemplateName>narrow_font_check</TemplateName>
			<Data>class39</Data>
			<LabelWidth>55</LabelWidth>
		</CheckBoxDef>
		<CheckBoxDef>
			<Position>
				<X>356</X>
				<Y>156</Y>
			</Position>
			<ControlId>1240</ControlId>
			<TemplateName>narrow_font_check</TemplateName>
			<Data>class40</Data>
			<LabelWidth>55</LabelWidth>
		</CheckBoxDef>
		<CheckBoxDef>
			<Position>
				<X>356</X>
				<Y>170</Y>
			</Position>
			<ControlId>1241</ControlId>
			<TemplateName>narrow_font_check</TemplateName>
			<Data>class41</Data>
			<LabelWidth>55</LabelWidth>
		</CheckBoxDef>
		<CheckBoxDef>
			<Position>
				<X>356</X>
				<Y>184</Y>
			</Position>
			<ControlId>1242</ControlId>
			<TemplateName>narrow_font_check</TemplateName>
			<Data>class42</Data>
			<LabelWidth>55</LabelWidth>
		</CheckBoxDef>
		<CheckBoxDef>
			<Position>
				<X>356</X>
				<Y>198</Y>
			</Position>
			<ControlId>1243</ControlId>
			<TemplateName>narrow_font_check</TemplateName>
			<Data>class43</Data>
			<LabelWidth>55</LabelWidth>
		</CheckBoxDef>
		<CheckBoxDef>
			<Position>
				<X>356</X>
				<Y>212</Y>
			</Position>
			<ControlId>1244</ControlId>
			<TemplateName>narrow_font_check</TemplateName>
			<Data>class44</Data>
			<LabelWidth>55</LabelWidth>
		</CheckBoxDef>
		<CheckBoxDef>
			<Position>
				<X>356</X>
				<Y>226</Y>
			</Position>
			<ControlId>1245</ControlId>
			<TemplateName>narrow_font_check</TemplateName>
			<Data>class45</Data>
			<LabelWidth>55</LabelWidth>
		</CheckBoxDef>
		<CheckBoxDef>
			<Position>
				<X>356</X>
				<Y>240</Y>
			</Position>
			<ControlId>1246</ControlId>
			<TemplateName>narrow_font_check</TemplateName>
			<Data>class46</Data>
			<LabelWidth>55</LabelWidth>
		</CheckBoxDef>
		<CheckBoxDef>
			<Position>
				<X>356</X>
				<Y>254</Y>
			</Position>
			<ControlId>1247</ControlId>
			<TemplateName>narrow_font_check</TemplateName>
			<Data>class47</Data>
			<LabelWidth>55</LabelWidth>
		</CheckBoxDef>
		<CheckBoxDef>
			<Position>
				<X>356</X>
				<Y>268</Y>
			</Position>
			<ControlId>1248</ControlId>
			<TemplateName>narrow_font_check</TemplateName>
			<Data>class48</Data>
			<LabelWidth>55</LabelWidth>
		</CheckBoxDef>
		<CheckBoxDef>
			<Position>
				<X>356</X>
				<Y>282</Y>
			</Position>
			<ControlId>1249</ControlId>
			<TemplateName>narrow_font_check</TemplateName>
			<Data>class49</Data>
			<LabelWidth>55</LabelWidth>
		</CheckBoxDef>
		<CheckBoxDef>
			<Position>
				<X>426</X>
				<Y>156</Y>
			</Position>
			<ControlId>1250</ControlId>
			<TemplateName>narrow_font_check</TemplateName>
			<Data>class50</Data>
			<LabelWidth>55</LabelWidth>
		</CheckBoxDef>
		<CheckBoxDef>
			<Position>
				<X>426</X>
				<Y>170</Y>
			</Position>
			<ControlId>1251</ControlId>
			<TemplateName>narrow_font_check</TemplateName>
			<Data>class51</Data>
			<LabelWidth>55</LabelWidth>
		</CheckBoxDef>
		<CheckBoxDef>
			<Position>
				<X>426</X>
				<Y>184</Y>
			</Position>
			<ControlId>1252</ControlId>
			<TemplateName>narrow_font_check</TemplateName>
			<Data>class52</Data>
			<LabelWidth>55</LabelWidth>
		</CheckBoxDef>
		<CheckBoxDef>
			<Position>
				<X>426</X>
				<Y>198</Y>
			</Position>
			<ControlId>1253</ControlId>
			<TemplateName>narrow_font_check</TemplateName>
			<Data>class53</Data>
			<LabelWidth>55</LabelWidth>
		</CheckBoxDef>
		<CheckBoxDef>
			<Position>
				<X>426</X>
				<Y>212</Y>
			</Position>
			<ControlId>1254</ControlId>
			<TemplateName>narrow_font_check</TemplateName>
			<Data>class54</Data>
			<LabelWidth>55</LabelWidth>
		</CheckBoxDef>
		<CheckBoxDef>
			<Position>
				<X>426</X>
				<Y>226</Y>
			</Position>
			<ControlId>1255</ControlId>
			<TemplateName>narrow_font_check</TemplateName>
			<Data>class55</Data>
			<LabelWidth>55</LabelWidth>
		</CheckBoxDef>
		<CheckBoxDef>
			<Position>
				<X>426</X>
				<Y>240</Y>
			</Position>
			<ControlId>1256</ControlId>
			<TemplateName>narrow_font_check</TemplateName>
			<Data>class56</Data>
			<LabelWidth>55</LabelWidth>
		</CheckBoxDef>
		<CheckBoxDef>
			<Position>
				<X>426</X>
				<Y>254</Y>
			</Position>
			<ControlId>1257</ControlId>
			<TemplateName>narrow_font_check</TemplateName>
			<Data>class57</Data>
			<LabelWidth>55</LabelWidth>
		</CheckBoxDef>
		<CheckBoxDef>
			<Position>
				<X>426</X>
				<Y>268</Y>
			</Position>
			<ControlId>1258</ControlId>
			<TemplateName>narrow_font_check</TemplateName>
			<Data>class58</Data>
			<LabelWidth>55</LabelWidth>
		</CheckBoxDef>
		<CheckBoxDef>
			<Position>
				<X>426</X>
				<Y>282</Y>
			</Position>
			<ControlId>1259</ControlId>
			<TemplateName>narrow_font_check</TemplateName>
			<Data>class59</Data>
			<LabelWidth>55</LabelWidth>
		</CheckBoxDef>
		<CheckBoxDef>
			<Position>
				<X>496</X>
				<Y>156</Y>
			</Position>
			<ControlId>1260</ControlId>
			<TemplateName>narrow_font_check</TemplateName>
			<Data>class60</Data>
			<LabelWidth>55</LabelWidth>
		</CheckBoxDef>
		<CheckBoxDef>
			<Position>
				<X>496</X>
				<Y>170</Y>
			</Position>
			<ControlId>1261</ControlId>
			<TemplateName>narrow_font_check</TemplateName>
			<Data>class61</Data>
			<LabelWidth>55</LabelWidth>
		</CheckBoxDef>
		<CheckBoxDef>
			<Position>
				<X>496</X>
				<Y>184</Y>
			</Position>
			<ControlId>1262</ControlId>
			<TemplateName>narrow_font_check</TemplateName>
			<Data>class62</Data>
			<LabelWidth>55</LabelWidth>
		</CheckBoxDef>
		<CheckBoxDef>
			<Position>
				<X>496</X>
				<Y>198</Y>
			</Position>
			<ControlId>1263</ControlId>
			<TemplateName>narrow_font_check</TemplateName>
			<Data>class63</Data>
			<LabelWidth>55</LabelWidth>
		</CheckBoxDef>
		<ButtonDef>
			<TemplateName>button_large</TemplateName>
			<ControlId>1002</ControlId>
			<Label>SEARCH</Label>
			<Position>
				<X>141</X>
				<Y>10</Y>
			</Position>
			<Alignment>
				<OffsetRight>true</OffsetRight>
				<OffsetBottom>true</OffsetBottom>
			</Alignment>
		</ButtonDef>
		<LabelDef>
			<Color>
				<R>192</R>
				<G>192</G>
				<B>192</B>
				<A>255</A>
			</Color>
			<FontName>arial11</FontName>
			<Width>75</Width>
			<Height>16</Height>
			<MaxCharacters>64</MaxCharacters>
			<Data>Min Level</Data>
			<Position>
				<X>13</X>
				<Y>87</Y>
			</Position>
		</LabelDef>
		<ButtonDef>
			<TemplateName>button_left</TemplateName>
			<ControlId>1005</ControlId>
			<Position>
				<X>74</X>
				<Y>85</Y>
			</Position>
		</ButtonDef>
		<ButtonDef>
			<TemplateName>button_right</TemplateName>
			<ControlId>1006</ControlId>
			<Position>
				<X>194</X>
				<Y>85</Y>
			</Position>
		</ButtonDef>
		<ScalarLabelDef>
			<Color>
				<R>192</R>
				<G>192</G>
				<B>192</B>
				<A>255</A>
			</Color>
			<FontName>arial11</FontName>
			<Width>104</Width>
			<Height>16</Height>
			<MaxCharacters>64</MaxCharacters>
			<Position>
				<X>90</X>
				<Y>87</Y>
			</Position>
			<Adapter>lfg_min_level</Adapter>
			<TextCentered>true</TextCentered>
		</ScalarLabelDef>
		<LabelDef>
			<Color>
				<R>192</R>
				<G>192</G>
				<B>192</B>
				<A>255</A>
			</Color>
			<FontName>arial11</FontName>
			<Width>75</Width>
			<Height>16</Height>
			<MaxCharacters>64</MaxCharacters>
			<Data>Max Level</Data>
			<Position>
				<X>13</X>
				<Y>105</Y>
			</Position>
		</LabelDef>
		<ButtonDef>
			<TemplateName>button_left</TemplateName>
			<ControlId>1007</ControlId>
			<Position>
				<X>74</X>
				<Y>103</Y>
			</Position>
		</ButtonDef>
		<ButtonDef>
			<TemplateName>button_right</TemplateName>
			<ControlId>1008</ControlId>
			<Position>
				<X>194</X>
				<Y>103</Y>
			</Position>
		</ButtonDef>
		<ScalarLabelDef>
			<Color>
				<R>192</R>
				<G>192</G>
				<B>192</B>
				<A>255</A>
			</Color>
			<FontName>arial11</FontName>
			<Width>104</Width>
			<Height>16</Height>
			<MaxCharacters>64</MaxCharacters>
			<Position>
				<X>90</X>
				<Y>105</Y>
			</Position>
			<Adapter>lfg_max_level</Adapter>
			<TextCentered>true</TextCentered>
		</ScalarLabelDef>
		<ButtonDef>
			<TemplateName>button_large</TemplateName>
			<ControlId>1000</ControlId>
			<Position>
				<X>225</X>
				<Y>6</Y>
			</Position>
			<Alignment>
				<OffsetRight>true</OffsetRight>
				<OffsetBottom>true</OffsetBottom>
			</Alignment>
			<Label>CLEAR</Label>
		</ButtonDef>
		<ButtonDef>
			<TemplateName>button_large</TemplateName>
			<ControlId>1004</ControlId>
			<Position>
				<X>155</X>
				<Y>6</Y>
			</Position>
			<Alignment>
				<OffsetRight>true</OffsetRight>
				<OffsetBottom>true</OffsetBottom>
			</Alignment>
			<Label>SUBMIT</Label>
		</ButtonDef>
		<CheckBoxDef>
			<Position>
				<X>13</X>
				<Y>25</Y>
			</Position>
			<ControlId>1017</ControlId>
			<TemplateName>generic_check</TemplateName>
			<Data>Looking For Players</Data>
			<LabelWidth>150</LabelWidth>
		</CheckBoxDef>
		<CheckBoxDef>
			<Position>
				<X>163</X>
				<Y>25</Y>
			</Position>
			<ControlId>1018</ControlId>
			<TemplateName>generic_check</TemplateName>
			<Data>Not Looking</Data>
			<LabelWidth>150</LabelWidth>
		</CheckBoxDef>
		<CheckBoxDef>
			<Position>
				<X>29</X>
				<Y>123</Y>
			</Position>
			<ControlId>1019</ControlId>
			<TemplateName>generic_check</TemplateName>
			<Data>Battlegroup</Data>
			<LabelWidth>150</LabelWidth>
		</CheckBoxDef>
		<LabelDef>
			<Color>
				<R>192</R>
				<G>192</G>
				<B>192</B>
				<A>192</A>
			</Color>
			<FontName>arial11</FontName>
			<Width>75</Width>
			<Height>16</Height>
			<MaxCharacters>64</MaxCharacters>
			<Data>Duration</Data>
			<Position>
				<X>13</X>
				<Y>66</Y>
			</Position>
		</LabelDef>
		<ComboBoxDef>
			<Position>
				<X>74</X>
				<Y>63</Y>
			</Position>
			<ControlId>1010</ControlId>
			<Templatename>combobox_thin</Templatename>
		</ComboBoxDef>
		<LabelDef>
			<Color>
				<R>192</R>
				<G>192</G>
				<B>192</B>
				<A>255</A>
			</Color>
			<FontName>arial11</FontName>
			<Width>75</Width>
			<Height>16</Height>
			<MaxCharacters>64</MaxCharacters>
			<Data>Objective</Data>
			<Position>
				<X>13</X>
				<Y>44</Y>
			</Position>
		</LabelDef>
		<ComboBoxDef>
			<Position>
				<X>74</X>
				<Y>41</Y>
			</Position>
			<ControlId>1009</ControlId>
			<Templatename>combobox_thin</Templatename>
		</ComboBoxDef>
	</WindowTemplate>
</Root_Element>
